mtbp3/.DS_Store
mtbp3/__init__.py
mtbp3/data/.DS_Store
mtbp3/data/attention.pdf
mtbp3/data/supp_ectd/fda_ectd3.2.2_ctocv2.3.3.txt
mtbp3/data/supp_ectd/fda_ectd4.0_ctocv1.0.txt
mtbp3/data/supp_seq/ICTV_MSL39v4_example.csv
mtbp3/data/supp_seq/ICTV_VMR_MSL39v4_example.csv
mtbp3/data/supp_seq/taxonomy_report.jsonl
mtbp3/data/supp_seq/taxonomy_summary.tsv
mtbp3/data/test_emt/FMQ/FMQ_Consolidated_List.csv
mtbp3/data/test_emt/MedDRA/!!readme_26_1_English.txt
mtbp3/data/test_emt/MedDRA/MedAscii/hlgt.asc
mtbp3/data/test_emt/MedDRA/MedAscii/hlgt_hlt.asc
mtbp3/data/test_emt/MedDRA/MedAscii/hlt.asc
mtbp3/data/test_emt/MedDRA/MedAscii/hlt_pt.asc
mtbp3/data/test_emt/MedDRA/MedAscii/intl_ord.asc
mtbp3/data/test_emt/MedDRA/MedAscii/llt.asc
mtbp3/data/test_emt/MedDRA/MedAscii/mdhier.asc
mtbp3/data/test_emt/MedDRA/MedAscii/meddra_history_english.asc
mtbp3/data/test_emt/MedDRA/MedAscii/meddra_release.asc
mtbp3/data/test_emt/MedDRA/MedAscii/pt.asc
mtbp3/data/test_emt/MedDRA/MedAscii/smq_content.asc
mtbp3/data/test_emt/MedDRA/MedAscii/smq_list.asc
mtbp3/data/test_emt/MedDRA/MedAscii/soc.asc
mtbp3/data/test_emt/MedDRA/MedAscii/soc_hlgt.asc
mtbp3/data/test_emt/MedDRA/SMQ_intguide_26_1_English.pdf
mtbp3/data/test_emt/MedDRA/SMQ_spreadsheet_26_1_English.xlsx
mtbp3/data/test_emt/MedDRA/SeqAscii/hlgt.seq
mtbp3/data/test_emt/MedDRA/SeqAscii/hlgt_hlt.seq
mtbp3/data/test_emt/MedDRA/SeqAscii/hlt.seq
mtbp3/data/test_emt/MedDRA/SeqAscii/hlt_pt.seq
mtbp3/data/test_emt/MedDRA/SeqAscii/intl_ord.seq
mtbp3/data/test_emt/MedDRA/SeqAscii/llt.seq
mtbp3/data/test_emt/MedDRA/SeqAscii/mdhier.seq
mtbp3/data/test_emt/MedDRA/SeqAscii/pt.seq
mtbp3/data/test_emt/MedDRA/SeqAscii/soc.seq
mtbp3/data/test_emt/MedDRA/SeqAscii/soc_hlgt.seq
mtbp3/data/test_emt/MedDRA/detail_report_26_1_English.pdf
mtbp3/data/test_emt/MedDRA/dist_file_format_26_1_English.pdf
mtbp3/data/test_emt/MedDRA/intguide_26_1_English.pdf
mtbp3/data/test_emt/MedDRA/version_report_26_1_English.xlsx
mtbp3/data/test_emt/MedDRA/whatsnew_26_1_English.pdf
mtbp3-0.2.31.dist-info/LICENSE
mtbp3-0.2.31.dist-info/METADATA
mtbp3-0.2.31.dist-info/WHEEL
mtbp3-0.2.31.dist-info/RECORD
