Metadata-Version: 2.1
Name: mtbp3
Version: 0.2.31
Summary: my tool box
License: GNU General Public License v3.0
Author: Y. Hsu
Requires-Python: >=3.10,<4.0
Classifier: License :: Other/Proprietary License
Classifier: Programming Language :: Python :: 3
Classifier: Programming Language :: Python :: 3.10
Classifier: Programming Language :: Python :: 3.11
Classifier: Programming Language :: Python :: 3.12
Classifier: Programming Language :: Python :: 3.13
Provides-Extra: docs
Requires-Dist: pandas (>=2.0.0,<3.0.0)
Requires-Dist: seaborn (>=0.13.2,<0.14.0)
